zemail/__init__.py
zemail-1.0.1.dist-info/METADATA
zemail-1.0.1.dist-info/WHEEL
zemail-1.0.1.dist-info/licenses/LICENSE
zemail-1.0.1.dist-info/RECORD
